python_phoenix_miner/__init__.py
python_phoenix_miner/base_client.py
python_phoenix_miner/phoenix_client.py
python_phoenix_miner/controllers/__init__.py
python_phoenix_miner/controllers/miner.py
python_phoenix_miner/models/__init__.py
python_phoenix_miner/models/miner/__init__.py
python_phoenix_miner/models/miner/extended_stats.py
python_phoenix_miner/models/miner/stats.py
python_phoenix_miner-0.0.2.dist-info/LICENSE
python_phoenix_miner-0.0.2.dist-info/METADATA
python_phoenix_miner-0.0.2.dist-info/WHEEL
python_phoenix_miner-0.0.2.dist-info/top_level.txt
python_phoenix_miner-0.0.2.dist-info/RECORD
