Metadata-Version: 2.1
Name: python-phoenix-miner
Version: 0.0.2
Summary: Phoenix Miner RPC API wrapper
Home-page: https://github.com/tekgeek88/python-phoenix-miner
Author: Carl Argabright
Author-email: carl.argabright@gmail.com
License: UNKNOWN
Project-URL: Bug Tracker, https://github.com/tekgeek88/python-phoenix-miner/issues
Platform: UNKNOWN
Classifier: Programming Language :: Python :: 3
Classifier: License :: OSI Approved :: MIT License
Classifier: Operating System :: OS Independent
Requires-Python: >=3.6
License-File: LICENSE
